{"info": {"team type": null, "cutoff": 1760.0, "cutoff deviation": 0, "metagame": "gen3uu", "number of battles": 13}, "data": {"Granbull": {"Moves": {"protect": 0.0, "return": 0.0, "metronome": 0.0, "smellingsalts": 7.45501834938378e-05, "shadowball": 0.0, "focuspunch": 7.45501834938378e-05, "counter": 0.0, "rest": 0.0, "sleeptalk": 0.0, "bodyslam": 7.45501834938378e-05, "healbell": 0.0, "earthquake": 0.0, "substitute": 7.45501834938378e-05}, "Checks and Counters": {}, "Abilities": {"intimidate": 7.45501834938378e-05}, "Teammates": {"Chimecho": 0.0, "Golem": 0.0, "Haunter": 0.0, "Primeape": 6.838459271057973e-05, "Grumpig": 6.838459271057973e-05, "Banette": 0.0, "Scyther": 0.0, "Fearow": 0.0, "Arcanine": 0.0, "Persian": 0.0, "Sandslash": 0.0, "Hitmonchan": 0.0, "Lunatone": 0.0, "Clefable": 6.838459271057973e-05, "Azumarill": 6.838459271057973e-05, "Mr. Mime": 0.0, "Vileplume": 0.0, "Rapidash": 6.838459271057973e-05, "Poliwrath": 0.0}, "usage": 0.000166, "Items": {"leftovers": 7.45501834938378e-05}, "Raw count": 13, "Spreads": {"Careful:200/148/56/0/104/0": 6.838459271057973e-05, "Sassy:248/0/8/0/252/0": 0.0, "Careful:0/252/104/0/150/0": 6.165590783258068e-06, "Impish:252/0/252/0/0/4": 0.0, "Impish:252/68/188/0/0/0": 0.0}, "Happiness": {"255": 7.45501834938378e-05}, "Viability Ceiling": [7, 60, 60, 55]}, "Primeape": {"Moves": {"counter": 0.0, "return": 6.838459271057973e-05, "dig": 0.0, "bulkup": 0.0, "aerialace": 6.838459271057973e-05, "crosschop": 6.838459271057973e-05, "hiddenpowerghost": 6.838459271057973e-05, "earthquake": 0.0}, "Checks and Counters": {}, "Abilities": {"vitalspirit": 6.838459271057973e-05}, "Teammates": {"Granbull": 6.838459271057973e-05, "Grumpig": 6.838459271057973e-05, "Altaria": 0.0, "Aggron": 0.0, "Arcanine": 0.0, "Rapidash": 6.838459271057973e-05, "Clefable": 6.838459271057973e-05, "Azumarill": 6.838459271057973e-05, "Electrode": 0.0, "empty": 0.0}, "usage": 0.000166, "Items": {"lumberry": 0.0, "choiceband": 6.838459271057973e-05}, "Raw count": 3, "Spreads": {"Jolly:4/252/0/0/0/252": 6.838459271057973e-05, "Hardy:116/140/148/0/0/104": 0.0}, "Happiness": {"255": 6.838459271057973e-05}, "Viability Ceiling": [2, 45, 45, 45]}, "Scyther": {"Moves": {"hiddenpowerbug": 0.0, "hiddenpowerground": 0.0, "return": 6.165590783258068e-06, "doubleedge": 0.0, "steelwing": 0.0, "aerialace": 6.165590783258068e-06, "swordsdance": 0.0223469806631153, "silverwind": 6.165590783258068e-06, "hiddenpowerflying": 0.0223469806631153, "substitute": 0.0223469806631153, "reversal": 0.0223469806631153, "morningsun": 0.0, "hiddenpowerrock": 0.0, "quickattack": 6.165590783258068e-06}, "Checks and Counters": {}, "Abilities": {"swarm": 0.02235314625389856}, "Teammates": {"Wailord": 0.0, "Banette": 0.0, "Fearow": 0.0, "Sandslash": 0.007820638069711228, "Kangaskhan": 0.007820638069711228, "Gorebyss": 0.007820638069711228, "Muk": 0.0, "Haunter": 0.0, "Camerupt": 0.0, "Ampharos": 0.0, "Shuckle": 0.0, "Hypno": 0.0, "Jumpluff": 0.0, "Hitmonchan": 0.0, "Granbull": 0.0, "Tentacruel": 0.0, "Misdreavus": 0.0, "Solrock": 0.0, "Lunatone": 0.0, "Azumarill": 0.0, "Vileplume": 0.0, "Glalie": 0.007820638069711228, "Chimecho": 0.0, "Murkrow": 0.0, "Arcanine": 0.0, "Omastar": 0.0, "Walrein": 0.0, "Electrode": 0.007820638069711228}, "usage": 0.0189873, "Items": {"liechiberry": 0.0, "salacberry": 0.0223469806631153, "choiceband": 6.165590783258068e-06, "lumberry": 0.0}, "Raw count": 14, "Spreads": {"Jolly:4/252/0/0/0/252": 0.02235314625389856, "Jolly:0/96/0/0/160/252": 0.0, "Jolly:0/252/0/0/4/252": 0.0}, "Happiness": {"255": 0.02235314625389856}, "Viability Ceiling": [8, 57, 57, 57]}, "Gorebyss": {"Moves": {"surf": 0.0223469806631153, "hydropump": 0.0223469806631153, "raindance": 0.0223469806631153, "psychic": 0.0223469806631153}, "Checks and Counters": {}, "Abilities": {"swiftswim": 0.0223469806631153}, "Teammates": {"Camerupt": 0.0, "Scyther": 0.007820638069711228, "Sandslash": 0.007820638069711228, "Kangaskhan": 0.007820638069711228, "Electrode": 0.007820638069711228, "Glalie": 0.007820638069711228}, "usage": 0.0189873, "Items": {"mysticwater": 0.0223469806631153}, "Raw count": 5, "Spreads": {"Timid:4/0/0/252/0/252": 0.0223469806631153}, "Happiness": {"255": 0.0223469806631153}, "Viability Ceiling": [2, 57, 57, 57]}, "Grumpig": {"Moves": {"magiccoat": 6.838459271057973e-05, "psychic": 6.838459271057973e-05, "firepunch": 6.838459271057973e-05, "calmmind": 6.838459271057973e-05}, "Checks and Counters": {}, "Abilities": {"owntempo": 6.838459271057973e-05}, "Teammates": {"Clefable": 6.838459271057973e-05, "Granbull": 6.838459271057973e-05, "Azumarill": 6.838459271057973e-05, "Primeape": 6.838459271057973e-05, "Rapidash": 6.838459271057973e-05}, "usage": 0.000166, "Items": {"leftovers": 6.838459271057973e-05}, "Raw count": 2, "Spreads": {"Calm:4/0/0/252/252/0": 6.838459271057973e-05}, "Happiness": {"255": 6.838459271057973e-05}, "Viability Ceiling": [1, 41, 41, 41]}, "Kangaskhan": {"Moves": {"return": 0.0, "shadowball": 0.0223469806631153, "rest": 0.0, "yawn": 0.0223469806631153, "doubleedge": 0.0223469806631153, "wish": 0.0, "toxic": 0.0, "earthquake": 0.0223469806631153}, "Checks and Counters": {}, "Abilities": {"earlybird": 0.0223469806631153}, "Teammates": {"Camerupt": 0.0, "Electrode": 0.007820638069711228, "Tentacruel": 0.0, "Solrock": 0.0, "Vileplume": 0.0, "Ampharos": 0.0, "Sandslash": 0.007820638069711228, "Scyther": 0.007820638069711228, "Gorebyss": 0.007820638069711228, "Glalie": 0.007820638069711228}, "usage": 0.0189873, "Items": {"leftovers": 0.0223469806631153}, "Raw count": 9, "Spreads": {"Adamant:0/252/0/0/4/252": 0.0223469806631153, "Careful:252/0/112/0/128/16": 0.0}, "Happiness": {"255": 0.0223469806631153}, "Viability Ceiling": [3, 57, 57, 57]}, "Misdreavus": {"Moves": {"thunderbolt": 6.165590783258068e-06, "shadowball": 0.4039992561835936, "psychic": 6.165590783258068e-06, "rest": 0.4039992561835936, "calmmind": 0.0, "imprison": 0.4039992561835936, "toxic": 0.4039992561835936, "destinybond": 6.165590783258068e-06, "substitute": 6.165590783258068e-06}, "Checks and Counters": {}, "Abilities": {"levitate": 0.40400542177437687}, "Teammates": {"Wailord": 0.0, "Scyther": 0.0, "Walrein": 0.4039992561835936, "Hypno": 0.0, "Arcanine": 0.0, "Lunatone": 0.0, "Ninjask": 0.4039992561835936, "Hitmontop": 0.4039992561835936, "Electrode": 0.4039992561835936, "Qwilfish": 0.4039992561835936}, "usage": 0.9808467000000001, "Items": {"leftovers": 0.40400542177437687}, "Raw count": 4, "Spreads": {"Calm:252/0/176/0/16/64": 0.0, "Timid:4/0/0/252/0/252": 6.165590783258068e-06, "Impish:252/4/252/0/0/0": 0.4039992561835936}, "Happiness": {"255": 0.40400542177437687}, "Viability Ceiling": [3, 72, 72, 72]}, "Sandslash": {"Moves": {"rockslide": 0.0223469806631153, "rest": 0.0, "swordsdance": 0.0223469806631153, "doubleedge": 0.0223469806631153, "rapidspin": 0.0, "toxic": 0.0, "earthquake": 0.0223469806631153}, "Checks and Counters": {}, "Abilities": {"sandveil": 0.0223469806631153}, "Teammates": {"Granbull": 0.0, "Gorebyss": 0.007820638069711228, "Scyther": 0.007820638069711228, "Arcanine": 0.0, "Vileplume": 0.0, "Lunatone": 0.0, "Kangaskhan": 0.007820638069711228, "Electrode": 0.007820638069711228, "Glalie": 0.007820638069711228, "Poliwrath": 0.0}, "usage": 0.0189873, "Items": {"leftovers": 0.0223469806631153}, "Raw count": 7, "Spreads": {"Jolly:4/252/0/0/0/252": 0.0223469806631153, "Careful:252/0/0/0/252/4": 0.0}, "Happiness": {"255": 0.0223469806631153}, "Viability Ceiling": [4, 55, 55, 55]}, "Rapidash": {"Moves": {"return": 6.838459271057973e-05, "quickattack": 6.838459271057973e-05, "bounce": 6.838459271057973e-05, "doublekick": 6.838459271057973e-05}, "Checks and Counters": {}, "Abilities": {"runaway": 6.838459271057973e-05}, "Teammates": {"Clefable": 6.838459271057973e-05, "Granbull": 6.838459271057973e-05, "Azumarill": 6.838459271057973e-05, "Primeape": 6.838459271057973e-05, "Grumpig": 6.838459271057973e-05}, "usage": 0.000166, "Items": {"choiceband": 6.838459271057973e-05}, "Raw count": 2, "Spreads": {"Adamant:4/252/0/0/0/252": 6.838459271057973e-05}, "Happiness": {"255": 6.838459271057973e-05}, "Viability Ceiling": [1, 41, 41, 41]}, "Walrein": {"Moves": {"surf": 0.0, "protect": 0.0, "rest": 0.4039992561835936, "sleeptalk": 0.4039992561835936, "icebeam": 0.4039992561835936, "toxic": 0.4039992561835936}, "Checks and Counters": {}, "Abilities": {"thickfat": 0.4039992561835936}, "Teammates": {"Arcanine": 0.0, "Scyther": 0.0, "Shuckle": 0.0, "Misdreavus": 0.4039992561835936, "Ampharos": 0.0, "Hitmontop": 0.4039992561835936, "Ninjask": 0.4039992561835936, "Electrode": 0.4039992561835936, "Qwilfish": 0.4039992561835936, "Muk": 0.0}, "usage": 0.9808467000000001, "Items": {"leftovers": 0.4039992561835936}, "Raw count": 3, "Spreads": {"Bold:252/0/252/4/0/0": 0.4039992561835936, "Calm:252/0/208/0/48/0": 0.0}, "Happiness": {"255": 0.4039992561835936}, "Viability Ceiling": [2, 72, 72, 72]}, "Clefable": {"Moves": {"thunderwave": 6.838459271057973e-05, "seismictoss": 6.838459271057973e-05, "cosmicpower": 6.838459271057973e-05, "softboiled": 6.838459271057973e-05}, "Checks and Counters": {}, "Abilities": {"cutecharm": 6.838459271057973e-05}, "Teammates": {"Granbull": 6.838459271057973e-05, "Azumarill": 6.838459271057973e-05, "Primeape": 6.838459271057973e-05, "Grumpig": 6.838459271057973e-05, "Rapidash": 6.838459271057973e-05}, "usage": 0.000166, "Items": {"pechaberry": 6.838459271057973e-05}, "Raw count": 2, "Spreads": {"Impish:252/0/152/0/104/0": 6.838459271057973e-05}, "Happiness": {"255": 6.838459271057973e-05}, "Viability Ceiling": [1, 41, 41, 41]}, "Hitmontop": {"Moves": {"hiddenpowerghost": 0.4039992561835936, "endeavor": 0.4039992561835936, "machpunch": 0.4039992561835936, "substitute": 0.4039992561835936}, "Checks and Counters": {}, "Abilities": {"intimidate": 0.4039992561835936}, "Teammates": {"Walrein": 0.4039992561835936, "Misdreavus": 0.4039992561835936, "Electrode": 0.4039992561835936, "Qwilfish": 0.4039992561835936, "Ninjask": 0.4039992561835936}, "usage": 0.9808467000000001, "Items": {"salacberry": 0.4039992561835936}, "Raw count": 2, "Spreads": {"Jolly:0/252/4/0/0/252": 0.4039992561835936}, "Happiness": {"255": 0.4039992561835936}, "Viability Ceiling": [1, 72, 72, 72]}, "Azumarill": {"Moves": {"hiddenpowerground": 6.838459271057973e-05, "return": 6.838459271057973e-05, "focuspunch": 6.838459271057973e-05, "hiddenpowerflying": 0.0, "brickbreak": 0.0, "substitute": 6.838459271057973e-05}, "Checks and Counters": {}, "Abilities": {"hugepower": 6.838459271057973e-05}, "Teammates": {"Granbull": 6.838459271057973e-05, "Primeape": 6.838459271057973e-05, "Grumpig": 6.838459271057973e-05, "Banette": 0.0, "Scyther": 0.0, "Omastar": 0.0, "Rapidash": 6.838459271057973e-05, "Clefable": 6.838459271057973e-05, "Murkrow": 0.0, "Jumpluff": 0.0}, "usage": 0.000166, "Items": {"leftovers": 6.838459271057973e-05, "choiceband": 0.0}, "Raw count": 3, "Spreads": {"Adamant:0/252/252/0/4/0": 0.0, "Adamant:130/252/60/0/63/0": 6.838459271057973e-05}, "Happiness": {"255": 6.838459271057973e-05}, "Viability Ceiling": [2, 55, 55, 55]}, "Electrode": {"Moves": {"explosion": 0.4263462368467089, "hiddenpowerice": 0.4263462368467089, "thunder": 0.0, "sonicboom": 0.0, "taunt": 0.0223469806631153, "thunderbolt": 0.4263462368467089, "spark": 0.0, "substitute": 0.4039992561835936}, "Checks and Counters": {}, "Abilities": {"static": 0.4263462368467089, "soundproof": 0.0}, "Teammates": {"Altaria": 0.0, "Primeape": 0.0, "Camerupt": 0.0, "Scyther": 0.007820638069711228, "Aggron": 0.0, "Walrein": 0.4039992561835936, "Misdreavus": 0.4039992561835936, "Arcanine": 0.0, "Sandslash": 0.007820638069711228, "Glalie": 0.007820638069711228, "Kangaskhan": 0.007820638069711228, "Hitmontop": 0.4039992561835936, "Gorebyss": 0.007820638069711228, "Qwilfish": 0.4039992561835936, "empty": 0.0, "Ninjask": 0.4039992561835936}, "usage": 0.999834, "Items": {"magnet": 0.0223469806631153, "petayaberry": 0.4039992561835936, "apicotberry": 0.0}, "Raw count": 8, "Spreads": {"Naive:0/100/0/192/0/216": 0.0223469806631153, "Hardy:100/0/100/158/0/150": 0.0, "Rash:12/32/116/252/0/96": 0.4039992561835936}, "Happiness": {"255": 0.4263462368467089}, "Viability Ceiling": [4, 72, 72, 72]}, "Qwilfish": {"Moves": {"sludgebomb": 0.4039992561835936, "destinybond": 0.4039992561835936, "spikes": 0.4039992561835936, "selfdestruct": 0.4039992561835936}, "Checks and Counters": {}, "Abilities": {"poisonpoint": 0.4039992561835936}, "Teammates": {"Hitmontop": 0.4039992561835936, "Walrein": 0.4039992561835936, "Ninjask": 0.4039992561835936, "Electrode": 0.4039992561835936, "Misdreavus": 0.4039992561835936}, "usage": 0.9808467000000001, "Items": {"leftovers": 0.4039992561835936}, "Raw count": 2, "Spreads": {"Jolly:236/0/0/0/20/252": 0.4039992561835936}, "Happiness": {"255": 0.4039992561835936}, "Viability Ceiling": [1, 72, 72, 72]}, "Glalie": {"Moves": {"spikes": 0.0223469806631153, "explosion": 0.0223469806631153, "earthquake": 0.0223469806631153, "hiddenpowergrass": 0.0223469806631153}, "Checks and Counters": {}, "Abilities": {"innerfocus": 0.0223469806631153}, "Teammates": {"Camerupt": 0.0, "Scyther": 0.007820638069711228, "Gorebyss": 0.007820638069711228, "Sandslash": 0.007820638069711228, "Kangaskhan": 0.007820638069711228, "Electrode": 0.007820638069711228}, "usage": 0.0189873, "Items": {"leftovers": 0.0223469806631153}, "Raw count": 5, "Spreads": {"Jolly:252/0/4/0/0/252": 0.0223469806631153}, "Happiness": {"255": 0.0223469806631153}, "Viability Ceiling": [2, 57, 57, 57]}, "Ninjask": {"Moves": {"protect": 0.0, "hiddenpowerice": 0.0, "aerialace": 0.4039992561835936, "swordsdance": 0.4039992561835936, "sleeptalk": 0.0, "silverwind": 0.4039992561835936, "hiddenpowerfighting": 0.4039992561835936}, "Checks and Counters": {}, "Abilities": {"speedboost": 0.4039992561835936}, "Teammates": {"Quagsire": 0.0, "Electabuzz": 0.0, "Exploud": 0.0, "Altaria": 0.0, "Misdreavus": 0.4039992561835936, "Nidoking": 0.0, "Walrein": 0.4039992561835936, "Hitmontop": 0.4039992561835936, "Electrode": 0.4039992561835936, "Qwilfish": 0.4039992561835936}, "usage": 0.9808467000000001, "Items": {"leftovers": 0.0, "lumberry": 0.4039992561835936}, "Raw count": 3, "Spreads": {"Adamant:4/252/0/0/0/252": 0.4039992561835936, "Timid:4/0/0/252/0/252": 0.0}, "Happiness": {"255": 0.4039992561835936}, "Viability Ceiling": [2, 72, 72, 72]}}}