{"info": {"metagame": "gen8nu", "cutoff": 1500.0, "cutoff deviation": 0, "team type": null, "number of battles": 1}, "data": {"Aerodactyl": {"Raw count": 1, "Viability Ceiling": [0, 0, 0, 0], "Abilities": {"unnerve": 0.5}, "Items": {"powerherb": 0.5}, "Spreads": {"Jolly:0/252/0/0/4/252": 0.5}, "Moves": {"dragondance": 0.5, "stoneedge": 0.5, "earthquake": 0.5, "skyattack": 0.5}, "Tera Types": {"nothing": 0.5}, "Happiness": {"255": 0.5}, "Teammates": {"Toxicroak": 0.628122801542395, "Dhelmise": 0.628122801542395, "Mudsdale": 0.628122801542395, "Copperajah": 0.628122801542395, "Vaporeon": 0.628122801542395}, "Checks and Counters": {}, "usage": 0.6281228}, "Toxicroak": {"Raw count": 1, "Viability Ceiling": [0, 0, 0, 0], "Abilities": {"dryskin": 0.5}, "Items": {"lifeorb": 0.5}, "Spreads": {"Modest:0/0/0/252/4/252": 0.5}, "Moves": {"nastyplot": 0.5, "focusblast": 0.5, "sludgebomb": 0.5, "shadowball": 0.5}, "Tera Types": {"nothing": 0.5}, "Happiness": {"255": 0.5}, "Teammates": {"Aerodactyl": 0.628122801542395, "Dhelmise": 0.628122801542395, "Mudsdale": 0.628122801542395, "Copperajah": 0.628122801542395, "Vaporeon": 0.628122801542395}, "Checks and Counters": {}, "usage": 0.6281228}, "Dhelmise": {"Raw count": 1, "Viability Ceiling": [0, 0, 0, 0], "Abilities": {"steelworker": 0.5}, "Items": {"heavydutyboots": 0.5}, "Spreads": {"Careful:252/12/0/0/136/108": 0.5}, "Moves": {"powerwhip": 0.5, "poltergeist": 0.5, "rapidspin": 0.5, "synthesis": 0.5}, "Tera Types": {"nothing": 0.5}, "Happiness": {"255": 0.5}, "Teammates": {"Aerodactyl": 0.628122801542395, "Toxicroak": 0.628122801542395, "Mudsdale": 0.628122801542395, "Copperajah": 0.628122801542395, "Vaporeon": 0.628122801542395}, "Checks and Counters": {}, "usage": 0.6281228}, "Mudsdale": {"Raw count": 1, "Viability Ceiling": [0, 0, 0, 0], "Abilities": {"stamina": 0.5}, "Items": {"leftovers": 0.5}, "Spreads": {"Impish:252/0/252/0/0/4": 0.5}, "Moves": {"stealthrock": 0.5, "earthquake": 0.5, "bodypress": 0.5, "toxic": 0.5}, "Tera Types": {"nothing": 0.5}, "Happiness": {"255": 0.5}, "Teammates": {"Aerodactyl": 0.628122801542395, "Toxicroak": 0.628122801542395, "Dhelmise": 0.628122801542395, "Copperajah": 0.628122801542395, "Vaporeon": 0.628122801542395}, "Checks and Counters": {}, "usage": 0.6281228}, "Copperajah": {"Raw count": 1, "Viability Ceiling": [0, 0, 0, 0], "Abilities": {"sheerforce": 0.5}, "Items": {"assaultvest": 0.5}, "Spreads": {"Adamant:0/252/0/0/88/168": 0.5}, "Moves": {"ironhead": 0.5, "powerwhip": 0.5, "superpower": 0.5, "rockslide": 0.5}, "Tera Types": {"nothing": 0.5}, "Happiness": {"255": 0.5}, "Teammates": {"Aerodactyl": 0.628122801542395, "Toxicroak": 0.628122801542395, "Dhelmise": 0.628122801542395, "Mudsdale": 0.628122801542395, "Vaporeon": 0.628122801542395}, "Checks and Counters": {}, "usage": 0.6281228}, "Vaporeon": {"Raw count": 1, "Viability Ceiling": [0, 0, 0, 0], "Abilities": {"waterabsorb": 0.5}, "Items": {"leftovers": 0.5}, "Spreads": {"Calm:252/0/216/0/40/0": 0.5}, "Moves": {"scald": 0.5, "healbell": 0.5, "wish": 0.5, "protect": 0.5}, "Tera Types": {"nothing": 0.5}, "Happiness": {"255": 0.5}, "Teammates": {"Aerodactyl": 0.628122801542395, "Toxicroak": 0.628122801542395, "Dhelmise": 0.628122801542395, "Mudsdale": 0.628122801542395, "Copperajah": 0.628122801542395}, "Checks and Counters": {}, "usage": 0.6281228}, "Clawitzer": {"Raw count": 1, "Viability Ceiling": [0, 0, 0, 0], "Abilities": {"megalauncher": 0.5}, "Items": {"leftovers": 0.5}, "Spreads": {"Modest:40/0/0/252/0/216": 0.5}, "Moves": {"waterpulse": 0.5, "dragonpulse": 0.5, "substitute": 0.5, "toxic": 0.5}, "Tera Types": {"nothing": 0.5}, "Happiness": {"255": 0.5}, "Teammates": {"Salazzle": 0.3718771984576051, "Sylveon": 0.3718771984576051, "Silvally-Ground": 0.3718771984576051, "Stakataka": 0.3718771984576051, "Rotom-Mow": 0.3718771984576051}, "Checks and Counters": {}, "usage": 0.37187719999999996}, "Salazzle": {"Raw count": 1, "Viability Ceiling": [0, 0, 0, 0], "Abilities": {"corrosion": 0.5}, "Items": {"heavydutyboots": 0.5}, "Spreads": {"Timid:4/0/0/252/0/252": 0.5}, "Moves": {"fireblast": 0.5, "sludgebomb": 0.5, "taunt": 0.5, "knockoff": 0.5}, "Tera Types": {"nothing": 0.5}, "Happiness": {"255": 0.5}, "Teammates": {"Clawitzer": 0.3718771984576051, "Sylveon": 0.3718771984576051, "Silvally-Ground": 0.3718771984576051, "Stakataka": 0.3718771984576051, "Rotom-Mow": 0.3718771984576051}, "Checks and Counters": {}, "usage": 0.37187719999999996}, "Sylveon": {"Raw count": 1, "Viability Ceiling": [0, 0, 0, 0], "Abilities": {"pixilate": 0.5}, "Items": {"leftovers": 0.5}, "Spreads": {"Calm:252/0/188/0/68/0": 0.5}, "Moves": {"hypervoice": 0.5, "wish": 0.5, "protect": 0.5, "healbell": 0.5}, "Tera Types": {"nothing": 0.5}, "Happiness": {"255": 0.5}, "Teammates": {"Clawitzer": 0.3718771984576051, "Salazzle": 0.3718771984576051, "Silvally-Ground": 0.3718771984576051, "Stakataka": 0.3718771984576051, "Rotom-Mow": 0.3718771984576051}, "Checks and Counters": {}, "usage": 0.37187719999999996}, "Silvally-Ground": {"Raw count": 1, "Viability Ceiling": [0, 0, 0, 0], "Abilities": {"rkssystem": 0.5}, "Items": {"groundmemory": 0.5}, "Spreads": {"Jolly:0/252/0/0/4/252": 0.5}, "Moves": {"defog": 0.5, "multiattack": 0.5, "rockslide": 0.5, "uturn": 0.5}, "Tera Types": {"nothing": 0.5}, "Happiness": {"255": 0.5}, "Teammates": {"Clawitzer": 0.3718771984576051, "Salazzle": 0.3718771984576051, "Sylveon": 0.3718771984576051, "Stakataka": 0.3718771984576051, "Rotom-Mow": 0.3718771984576051}, "Checks and Counters": {}, "usage": 0.37187719999999996}, "Stakataka": {"Raw count": 1, "Viability Ceiling": [0, 0, 0, 0], "Abilities": {"beastboost": 0.5}, "Items": {"leftovers": 0.5}, "Spreads": {"Sassy:252/4/0/0/252/0": 0.5}, "Moves": {"stealthrock": 0.5, "rockblast": 0.5, "heatcrash": 0.5, "toxic": 0.5}, "Tera Types": {"nothing": 0.5}, "Happiness": {"255": 0.5}, "Teammates": {"Clawitzer": 0.3718771984576051, "Salazzle": 0.3718771984576051, "Sylveon": 0.3718771984576051, "Silvally-Ground": 0.3718771984576051, "Rotom-Mow": 0.3718771984576051}, "Checks and Counters": {}, "usage": 0.37187719999999996}, "Rotom-Mow": {"Raw count": 1, "Viability Ceiling": [0, 0, 0, 0], "Abilities": {"levitate": 0.5}, "Items": {"choicescarf": 0.5}, "Spreads": {"Timid:8/0/0/248/0/252": 0.5}, "Moves": {"leafstorm": 0.5, "voltswitch": 0.5, "trick": 0.5, "nastyplot": 0.5}, "Tera Types": {"nothing": 0.5}, "Happiness": {"255": 0.5}, "Teammates": {"Clawitzer": 0.3718771984576051, "Salazzle": 0.3718771984576051, "Sylveon": 0.3718771984576051, "Silvally-Ground": 0.3718771984576051, "Stakataka": 0.3718771984576051}, "Checks and Counters": {}, "usage": 0.37187719999999996}}}