{"Raging Bolt":{"Fairy":337,"Electric":124,"Bug":5,"Grass":12,"Normal":5,"Water":10,"Steel":2,"Dark":5,"Flying":3,"Ice":1,"Ground":2,"Stellar":1},"Flutter Mane":{"Fairy":746,"Water":9,"Grass":13,"Stellar":20,"Normal":7,"Ghost":12,"Steel":7,"Dark":3,"Flying":1,"Dragon":1},"Landorus-Therian":{"Ground":6,"Flying":33,"Water":5,"Poison":1,"Ice":2,"Stellar":1,"Steel":2,"Ghost":2,"Fairy":1,"Fire":1},"Ursaluna-Bloodmoon":{"Normal":275,"Ghost":6,"Fairy":4,"Grass":4,"Poison":1,"Stellar":1,"Bug":1},"Annihilape":{"Steel":7,"Fire":10,"Water":3,"Grass":2,"Fighting":4,"Normal":2,"Electric":1,"Ghost":2},"Indeedee-F":{"Fairy":59,"Grass":18,"Water":21,"Fire":8,"Dark":1,"Normal":2,"Dragon":1,"Bug":1},"Miraidon":{"Fairy":345,"Electric":202,"Ice":6,"Ghost":16,"Normal":1,"Steel":17,"Fire":9,"Grass":12,"Psychic":1,"Ground":1,"Water":7,"Stellar":3,"Flying":2,"Dark":2,"Bug":1},"Ninetales-Alola":{"Dark":3,"Fire":23,"Ice":2,"Water":10,"Ghost":17,"Ground":2,"Normal":1},"Calyrex-Ice":{"Water":516,"Dragon":19,"Grass":63,"Fire":289,"Fairy":31,"Ice":79,"Electric":7,"Ground":18,"Dark":11,"Fighting":9,"Psychic":4,"Normal":20,"Flying":3,"Poison":4,"Steel":1,"Ghost":3},"Terapagos":{"Stellar":988},"Kingambit":{"Fairy":59,"Psychic":2,"Dragon":24,"Dark":43,"Fire":3,"Ghost":8,"Flying":17,"Water":11,"Bug":2,"Grass":1,"Poison":1,"Electric":1,"Steel":1},"Roaring Moon":{"Flying":28,"Fire":2,"Steel":5,"Poison":13,"Ghost":7,"Fairy":1,"Water":1},"Calyrex-Shadow":{"Ghost":379,"Normal":72,"Fairy":560,"Fighting":48,"Bug":2,"Psychic":17,"Dark":31,"Grass":6,"Water":4,"Stellar":8,"Fire":3,"Poison":1,"Steel":3,"Flying":1,"Ground":3},"Landorus":{"Poison":159,"Steel":54,"Ground":4,"Grass":5,"Water":10,"Fairy":1,"Ghost":2,"Fighting":1,"Flying":4},"Sinistcha":{"Water":16,"Fairy":5,"Fire":2,"Normal":1,"Bug":1,"Grass":2,"Dark":1,"Poison":1},"Kyurem-White":{"Fire":37,"Ice":88,"Steel":3,"Fairy":6,"Poison":4,"Ghost":3,"Dragon":3,"Water":4,"Ground":1},"Typhlosion-Hisui":{"Fire":8,"Grass":1},"Kyogre":{"Grass":389,"Water":250,"Electric":24,"Steel":9,"Flying":7,"Dragon":8,"Fire":2,"Poison":2,"Bug":1,"Fairy":6,"Ground":1,"Dark":1,"Ghost":3,"Ice":2},"Torkoal":{"Fire":94,"Water":1,"Grass":4},"Zamazenta-Crowned":{"Water":131,"Fighting":13,"Grass":22,"Ghost":39,"Flying":7,"Fairy":30,"Dragon":8,"Steel":2,"Fire":3,"Bug":2,"Stellar":1},"Incineroar":{"Grass":170,"Ghost":444,"Water":92,"Fire":9,"Dragon":16,"Fighting":1,"Fairy":16,"Poison":2,"Normal":1,"Dark":2,"Steel":1,"Flying":1},"Rayquaza":{"Normal":134,"Steel":5,"Flying":2,"Dragon":1,"Fire":2,"Water":1},"Kyurem-Black":{"Dragon":4,"Electric":12,"Fairy":7,"Poison":3,"Fire":5,"Rock":1,"Ground":1,"Steel":1,"Water":1,"Ghost":1},"Groudon":{"Fire":393,"Water":29,"Grass":35,"Steel":35,"Fairy":19,"Ground":6,"Ghost":8,"Stellar":1,"Dragon":8,"Poison":2,"Electric":1,"Normal":1},"Walking Wake":{"Fire":59,"Steel":22,"Fairy":8,"Water":43,"Poison":4,"Ground":2,"Ghost":1},"Zacian-Crowned":{"Fairy":62,"Water":62,"Steel":11,"Stellar":58,"Fire":6,"Flying":7,"Ghost":6,"Dragon":6,"Grass":17,"Ground":2,"Fighting":11,"Poison":1,"Normal":1},"Rillaboom":{"Grass":74,"Water":38,"Fire":230,"Poison":17,"Ground":2,"Ghost":7,"Dragon":2,"Normal":7,"Electric":1,"Steel":3,"Flying":1,"Dark":1},"Venusaur":{"Fire":18,"Ghost":6,"Water":9,"Ground":3,"Grass":1,"Poison":2,"Dark":2},"Solgaleo":{"Steel":3,"Dragon":1,"Flying":1,"Dark":3,"Water":7,"Fire":3,"Psychic":1},"Tornadus":{"Flying":29,"Steel":84,"Dark":72,"Ghost":38,"Normal":2,"Grass":1,"Fighting":1,"Dragon":2,"Fire":2,"Ground":6,"Poison":1,"Ice":3,"Rock":1,"Water":2},"Ogerpon-Cornerstone":{"Rock":30},"Urshifu-Rapid-Strike":{"Water":532,"Fairy":2,"Ice":3,"Poison":3,"Ghost":40,"Steel":74,"Fire":15,"Grass":48,"Fighting":15,"Stellar":4},"Chien-Pao":{"Stellar":49,"Ghost":86,"Fighting":3,"Electric":6,"Water":2,"Dark":8,"Ground":1},"Amoonguss":{"Water":361,"Grass":2,"Dark":73,"Fire":7,"Fairy":23,"Normal":3,"Dragon":1,"Steel":1,"Poison":1,"Electric":1,"Ghost":3},"Arcanine-Hisui":{"Grass":12,"Fairy":4,"Ghost":5,"Normal":9,"Psychic":1,"Fire":3,"Water":2,"Rock":1,"Stellar":1},"Hitmontop":{"Fighting":2,"Steel":2,"Dark":1,"Fire":1},"Smeargle":{"Grass":7,"Ghost":13},"Mienshao":{"Ghost":2,"Fighting":12,"Stellar":2,"Steel":4},"Uxie":{"Ghost":1},"Pelipper":{"Grass":7,"Steel":9,"Stellar":14,"Ghost":22,"Ground":2,"Flying":2,"Electric":1,"Dragon":1},"Dragonite":{"Normal":103,"Steel":3,"Fairy":1,"Dragon":2,"Flying":2,"Ground":1},"Eternatus":{"Poison":11,"Fairy":27,"Ice":3,"Dark":15,"Water":11,"Normal":2,"Ghost":1,"Grass":5,"Rock":1,"Stellar":4,"Steel":3,"Fire":2},"Araquanid":{"Water":32,"Bug":1},"Iron Jugulis":{"Steel":13,"Grass":4,"Fire":2,"Poison":7,"Water":1,"Dark":1,"Ground":2,"Ghost":3,"Normal":1},"Ogerpon-Hearthflame":{"Fire":368},"Tyranitar":{"Flying":38,"Grass":8,"Rock":3,"Fairy":4,"Water":2,"Fighting":1,"Ghost":3,"Steel":1,"Bug":1,"Psychic":1},"Great Tusk":{"Steel":3,"Ground":5,"Fighting":1,"Rock":1,"Ice":1,"Fairy":1,"Fire":1},"Urshifu":{"Poison":21,"Dark":155,"Ghost":8,"Stellar":9,"Fire":3,"Grass":2,"Steel":4,"Fighting":6,"Fairy":2,"Normal":1,"Water":1},"Scream Tail":{"Steel":2,"Bug":3,"Normal":3,"Dark":2,"Ghost":1},"Porygon2":{"Poison":27,"Normal":1,"Ghost":9,"Fairy":9,"Dark":2,"Flying":3},"Wo-Chien":{"Water":17,"Fire":5,"Poison":12,"Fairy":4,"Dark":1},"Lunala":{"Fairy":157,"Normal":15,"Grass":2,"Dark":11,"Ghost":3,"Psychic":3,"Rock":1,"Ice":1,"Poison":1},"Chi-Yu":{"Ghost":133,"Dark":5,"Water":24,"Fire":46,"Grass":15,"Ground":4,"Fairy":3},"Iron Moth":{"Fairy":3,"Rock":1,"Grass":17,"Fire":2,"Flying":1,"Ghost":1,"Bug":3,"Dragon":1,"Water":1,"Dark":1},"Koraidon":{"Steel":30,"Fire":409,"Ground":1,"Fairy":8,"Fighting":7,"Normal":2,"Poison":1,"Flying":1,"Ghost":1},"Talonflame":{"Flying":2,"Ghost":1},"Dudunsparce":{"Normal":1},"Corviknight":{"Flying":2,"Fairy":4,"Fighting":1,"Ground":5,"Dragon":2,"Fire":2},"Lugia":{"Steel":9,"Grass":2,"Fairy":12,"Electric":2,"Dragon":3,"Normal":5,"Water":1,"Flying":4,"Dark":3,"Poison":1,"Ground":2,"Fire":1,"Psychic":1,"Ice":1},"Dondozo":{"Dragon":15,"Grass":39,"Fairy":8,"Fire":1,"Water":3,"Ground":2,"Steel":2,"Poison":2,"Bug":1,"Ghost":1},"Slowbro":{"Dark":3,"Fairy":2,"Normal":1},"Ogerpon-Wellspring":{"Water":432},"Necrozma-Dusk-Mane":{"Dark":3,"Fairy":5,"Ground":1,"Water":11,"Fire":2,"Flying":2,"Normal":4,"Steel":2,"Dragon":1,"Grass":1},"Farigiraf":{"Water":19,"Fairy":120,"Normal":22,"Dark":5,"Fire":6,"Grass":7,"Dragon":1,"Fighting":1,"Ground":1},"Brute Bonnet":{"Water":18,"Fairy":2,"Poison":6,"Fire":10,"Grass":1,"Dark":3},"Gholdengo":{"Fairy":22,"Dark":2,"Steel":37,"Normal":8,"Dragon":19,"Water":11},"Comfey":{"Grass":1,"Steel":5,"Fairy":1,"Ghost":1},"Hydrapple":{"Fire":2,"Water":1,"Steel":1},"Okidogi":{"Fire":1,"Dark":5,"Poison":1,"Water":2,"Grass":2,"Normal":1},"Garganacl":{"Fairy":6,"Ghost":11,"Dragon":4,"Bug":5,"Water":4,"Flying":2,"Steel":2,"Poison":4,"Fire":1,"Grass":5,"Psychic":1,"Normal":2},"Iron Boulder":{"Dragon":4,"Grass":18,"Ground":1,"Fighting":5,"Rock":4,"Water":1,"Fire":1,"Fairy":2,"Steel":1},"Garchomp":{"Ice":1,"Steel":3,"Water":2},"Dialga-Origin":{"Fairy":11,"Ghost":6,"Grass":5,"Water":2,"Bug":4,"Dragon":1,"Steel":3,"Electric":1,"Flying":1},"Dusclops":{"Fairy":2,"Dark":3,"Grass":1},"Heatran":{"Grass":28,"Fairy":2,"Flying":1,"Fire":1,"Bug":1},"Archaludon":{"Stellar":2,"Grass":25,"Fighting":2,"Fairy":93,"Bug":9,"Steel":3,"Water":5,"Electric":8,"Flying":9,"Normal":1,"Ghost":1,"Dragon":3},"Overqwil":{"Ice":1,"Water":2,"Dark":2},"Ursaluna":{"Ghost":39,"Normal":24,"Fairy":7,"Dragon":2,"Steel":1,"Water":3,"Poison":3,"Stellar":1,"Ground":3,"Grass":1},"Reshiram":{"Fairy":8,"Ground":1,"Fire":10,"Steel":1,"Stellar":1,"Ghost":1,"Grass":3},"Ting-Lu":{"Fairy":24,"Poison":49,"Bug":3,"Grass":1,"Dark":2,"Steel":2,"Water":1},"Exeggutor-Alola":{"Steel":4,"Grass":1,"Fire":1},"Bronzong":{"Electric":2,"Fire":9,"Grass":3,"Water":2,"Normal":1,"Steel":1,"Fairy":2,"Fighting":1,"Dark":1},"Vaporeon":{"Poison":2,"Water":1},"Iron Hands":{"Steel":2,"Fighting":10,"Water":30,"Grass":45,"Flying":3,"Fire":14,"Ice":2,"Fairy":2,"Ground":2,"Electric":1},"Dewgong":{"Electric":1,"Grass":1},"Kommo-o":{"Steel":18,"Dragon":2,"Normal":1,"Fire":2,"Fairy":1},"Entei":{"Normal":71,"Fire":3,"Dragon":1,"Grass":12,"Fairy":2,"Water":1},"Fezandipiti":{"Water":1,"Grass":4},"Oricorio":{"Dark":1},"Iron Valiant":{"Stellar":1,"Ghost":11,"Fairy":2,"Fighting":1,"Steel":5,"Psychic":4,"Water":1},"Terapagos-Terastal":{"Stellar":142},"Necrozma-Dawn-Wings":{"Psychic":16,"Water":11,"Fighting":1,"Normal":6,"Fairy":4,"Dark":6,"Stellar":1},"Hitmonlee":{"Fire":1},"Sandy Shocks":{"Grass":3,"Steel":1,"Electric":5,"Ghost":3},"Ho-Oh":{"Grass":37,"Dragon":11,"Fairy":8,"Normal":1,"Steel":7,"Flying":1,"Ground":2,"Rock":1,"Water":6,"Fire":2,"Dark":1,"Poison":1},"Slowking-Galar":{"Bug":1,"Poison":1,"Water":1,"Normal":1},"Goodra-Hisui":{"Water":6,"Fairy":6,"Dragon":2,"Steel":1},"Iron Bundle":{"Ground":3,"Ghost":46,"Grass":5,"Ice":23,"Water":2,"Electric":2,"Steel":1},"Hatterene":{"Fire":7,"Psychic":8,"Steel":1,"Fairy":2,"Water":3,"Stellar":1},"Glastrier":{"Ground":1,"Poison":1,"Steel":2,"Water":1},"Sinistcha-Masterpiece":{"Grass":1,"Poison":1,"Water":4},"Gouging Fire":{"Fairy":25,"Grass":12,"Ghost":1,"Fire":11,"Ground":1,"Water":2,"Poison":1,"Dark":1,"Ice":1},"Mewtwo":{"Ice":3,"Stellar":5,"Psychic":3,"Dark":3,"Fairy":1,"Ghost":1,"Fighting":1,"Normal":1},"Palkia":{"Fairy":3,"Water":1,"Dragon":1,"Fire":1},"Zapdos-Galar":{"Poison":1,"Ghost":2,"Flying":3,"Steel":8,"Electric":1,"Fire":1,"Grass":1,"Fairy":1},"Gastrodon":{"Fire":11,"Poison":3,"Flying":1,"Bug":1,"Grass":1},"Serperior":{"Rock":3,"Steel":1,"Dragon":3,"Electric":1,"Dark":1,"Fire":1,"Water":2},"Abomasnow":{"Fire":1,"Electric":1,"Water":2},"Articuno":{"Ice":19},"Gothitelle":{"Dark":2,"Steel":4,"Water":1,"Fairy":2},"Basculegion":{"Dark":1,"Grass":3,"Water":8,"Ghost":1,"Fairy":2},"Lucario":{"Normal":2,"Fighting":3},"Moltres":{"Fire":2},"Volcarona":{"Grass":7,"Fairy":4,"Dark":3,"Water":2,"Dragon":2},"Weezing":{"Poison":1,"Ghost":3,"Flying":1},"Inteleon":{"Grass":1,"Dragon":1,"Normal":1},"Skeledirge":{"Fairy":6,"Grass":4,"Normal":2,"Water":3,"Dragon":1},"Slither Wing":{"Fighting":1,"Fire":3},"Enamorus-Therian":{"Stellar":2,"Fairy":6,"Flying":1,"Electric":1},"Lilligant-Hisui":{"Ghost":20,"Steel":1,"Fighting":1,"Grass":2},"Gallade":{"Fire":5,"Normal":1,"Grass":18,"Dark":2,"Steel":1,"Water":1,"Poison":1},"Armarouge":{"Psychic":5,"Grass":19,"Fire":3,"Ghost":1,"Dark":2,"Water":4,"Fairy":2},"Braviary-Hisui":{"Fire":3,"Fairy":2,"Psychic":1},"Milotic":{"Grass":8,"Dragon":2,"Fairy":2,"Water":1},"Empoleon":{"Ghost":2,"Fairy":1,"Stellar":1,"Water":3,"Grass":1,"Flying":1},"Thundurus":{"Ghost":2,"Steel":4,"Dark":5,"Electric":2,"Water":1},"Cresselia":{"Fairy":17,"Dark":3,"Ghost":1,"Electric":1,"Poison":2},"Suicune":{"Dark":2,"Grass":7,"Fire":1,"Dragon":1},"Clefairy":{"Water":6,"Steel":4,"Grass":7,"Normal":2},"Scrafty":{"Fairy":1,"Steel":2,"Ghost":1,"Fire":2},"Grimmsnarl":{"Steel":5,"Ghost":10,"Fire":2,"Grass":1},"Breloom":{"Water":1,"Ghost":3,"Grass":1},"Drifblim":{"Dark":3},"Necrozma":{"Fairy":1},"Conkeldurr":{"Grass":3,"Electric":1},"Rotom-Heat":{"Poison":1,"Fire":1},"Umbreon":{"Fairy":5,"Poison":10,"Ghost":1},"Charizard":{"Fire":7,"Poison":1,"Ground":2,"Steel":2,"Fairy":1},"Rampardos":{"Electric":1,"Rock":1},"Latias":{"Steel":4,"Poison":3,"Normal":1,"Dragon":1,"Fairy":1},"Slaking":{"Normal":3,"Ghost":3,"Grass":1},"Orthworm":{"Fire":4,"Ground":1,"Poison":2,"Water":1,"Normal":1},"Glimmora":{"Flying":2,"Rock":1,"Grass":23,"Water":1,"Ghost":1,"Dragon":1,"Stellar":2,"Fairy":1,"Psychic":1},"Coalossal":{"Water":3,"Dark":1,"Grass":2},"Regieleki":{"Electric":5,"Ghost":2,"Ice":7,"Normal":1},"Iron Thorns":{"Grass":1},"Falinks":{"Steel":2},"Raichu-Alola":{"Grass":2,"Stellar":2},"Baxcalibur":{"Ghost":1,"Dragon":1,"Grass":1,"Poison":2,"Fairy":3,"Ground":1},"Trevenant":{"Ground":1,"Fairy":1,"Fire":1},"Enamorus":{"Fairy":2,"Fighting":3,"Stellar":6},"Gyarados":{"Ground":5,"Dragon":1,"Water":2,"Ghost":1,"Flying":1,"Dark":1},"Sableye":{"Normal":2},"Giratina-Origin":{"Ghost":3,"Poison":4,"Steel":4,"Fairy":7,"Electric":1},"Gogoat":{"Water":1},"Leafeon":{"Fire":2,"Rock":2},"Electivire":{"Water":1,"Stellar":1,"Flying":1},"Whimsicott":{"Steel":2,"Fairy":2,"Ghost":5,"Dark":2,"Poison":1,"Water":2,"Normal":1},"Vivillon":{"Bug":1},"Lanturn":{"Flying":1},"Cinderace":{"Fire":3,"Fairy":1},"Frosmoth":{"Fairy":1,"Ground":2,"Water":6},"Oranguru":{"Grass":2,"Fairy":7,"Water":1},"Hariyama":{"Steel":1,"Normal":1},"Chesnaught":{"Steel":7,"Fire":4},"Tsareena":{"Water":3,"Fire":6,"Steel":1,"Ice":1},"Scizor":{"Normal":1,"Water":2,"Fire":2,"Fairy":1,"Rock":1,"Dragon":1,"Steel":2,"Dark":1},"Sneasler":{"Fighting":2,"Flying":4,"Dark":2,"Ghost":1,"Poison":1},"Golem-Alola":{"Electric":1},"Zekrom":{"Fairy":3,"Rock":2,"Water":2,"Dragon":1},"Vikavolt":{"Electric":2,"Water":3},"Chandelure":{"Fire":2,"Grass":1,"Ghost":1},"Dudunsparce-Three-Segment":{"Ghost":1},"Muk-Alola":{"Water":5,"Fairy":1,"Steel":1,"Flying":1,"Dark":1,"Poison":1},"Crabominable":{"Stellar":1},"Ogerpon":{"Grass":39},"Swampert":{"Fire":1,"Steel":1,"Grass":1},"Articuno-Galar":{"Normal":1,"Ground":5,"Fighting":1,"Ghost":1,"Fairy":2,"Psychic":1},"Espathra":{"Fighting":1,"Dark":1,"Fairy":6},"Appletun":{"Steel":3},"Thundurus-Therian":{"Steel":2,"Fairy":1,"Stellar":1,"Water":1},"Blaziken":{"Fighting":1,"Electric":1,"Steel":2},"Gastrodon-East":{"Fire":5,"Poison":2},"Typhlosion":{"Fire":4,"Ghost":1},"Jolteon":{"Electric":1},"Ludicolo":{"Stellar":1,"Steel":1,"Water":1},"Toedscruel":{"Fairy":1,"Water":1},"Maushold-Four":{"Ghost":1,"Normal":3},"Kleavor":{"Grass":1,"Rock":3,"Bug":1},"Regigigas":{"Normal":1,"Ghost":6,"Electric":1,"Water":1},"Tatsugiri":{"Fairy":2,"Water":1,"Dragon":1,"Normal":1},"Registeel":{"Water":8,"Dragon":1,"Fighting":1,"Flying":1},"Salamence":{"Poison":1,"Steel":4,"Rock":1,"Electric":1},"Metagross":{"Steel":4,"Water":2,"Normal":2,"Dark":1},"Dachsbun":{"Steel":1,"Fighting":1},"Kilowattrel":{"Ghost":1,"Electric":2},"Flamigo":{"Bug":2,"Steel":4,"Flying":1,"Dark":1},"Zoroark-Hisui":{"Stellar":1},"Regice":{"Water":3,"Fighting":1,"Electric":1,"Ghost":1},"Moltres-Galar":{"Ground":1,"Dark":10,"Steel":2,"Fire":1,"Poison":6,"Fairy":1},"Electrode-Hisui":{"Normal":1,"Electric":1,"Water":1},"Indeedee":{"Fairy":1},"Primarina":{"Electric":2,"Grass":3,"Steel":3,"Water":1,"Dragon":2},"Munkidori":{"Poison":3},"Excadrill":{"Flying":1,"Ground":3,"Fairy":1},"Palafin-Hero":{"Water":7},"Porygon-Z":{"Ice":1,"Ghost":4,"Fighting":1},"Dragapult":{"Ghost":5,"Steel":2,"Dragon":1},"Clodsire":{"Poison":1,"Fire":2,"Dark":2},"Eelektross":{"Electric":2},"Iron Leaves":{"Fairy":2,"Steel":1,"Dark":2,"Water":2,"Fire":1,"Normal":1,"Psychic":1},"Rhyperior":{"Grass":1,"Fairy":4,"Water":4,"Fire":3,"Flying":1,"Rock":1},"Lycanroc":{"Flying":1,"Rock":1,"Grass":1,"Ghost":1},"Ceruledge":{"Grass":7,"Fairy":1,"Water":2,"Steel":1,"Normal":1},"Passimian":{"Dark":1,"Rock":1},"Dialga":{"Fairy":1,"Ghost":1,"Steel":2,"Stellar":1},"Terrakion":{"Grass":2,"Flying":1,"Steel":1,"Ghost":1},"Braviary":{"Steel":1},"Malamar":{"Fighting":2},"Iron Crown":{"Water":4,"Dark":2,"Steel":2,"Fire":1,"Psychic":1,"Fighting":1},"Magmar":{"Fairy":1,"Grass":2},"Sceptile":{"Flying":1,"Fire":2},"Delphox":{"Fire":2,"Grass":1},"Murkrow":{"Ghost":1},"Samurott-Hisui":{"Steel":1,"Fairy":1,"Grass":1},"Infernape":{"Ghost":1,"Fire":1},"Zapdos":{"Steel":3,"Fire":2,"Water":1,"Electric":1},"Sylveon":{"Fairy":4,"Water":2},"Palkia-Origin":{"Steel":4,"Water":1,"Dragon":1},"Iron Treads":{"Ground":3,"Ghost":1},"Jumpluff":{"Water":2,"Ghost":1,"Rock":1,"Normal":1},"Azumarill":{"Water":2,"Fairy":1,"Flying":1,"Grass":1},"Yanmega":{"Ground":1},"Goodra":{"Dragon":1,"Poison":1},"Ditto":{"Stellar":2,"Water":1,"Ghost":2,"Fairy":1,"Normal":5},"Ribombee":{"Fairy":1},"Rotom-Wash":{"Grass":1,"Ghost":1},"Mamoswine":{"Fairy":2,"Grass":1,"Ice":1,"Water":1},"Regidrago":{"Steel":4,"Dragon":2},"Beartic":{"Normal":2,"Ground":1},"Slowking":{"Dark":1,"Fairy":1,"Poison":1},"Arcanine":{"Normal":3,"Grass":1},"Noivern":{"Flying":1,"Normal":2},"Tentacruel":{"Ice":1,"Water":1},"Politoed":{"Dragon":2,"Grass":1},"Ninetales":{"Fire":1},"Shiftry":{"Grass":1,"Dark":2,"Ghost":6},"Snorlax":{"Fairy":1,"Grass":2,"Electric":1,"Poison":1},"Weezing-Galar":{"Normal":1,"Dark":1,"Poison":1},"Latios":{"Poison":1,"Fire":1,"Steel":1},"Zangoose":{"Normal":1},"Gliscor":{"Rock":1,"Steel":2,"Stellar":1,"Water":1},"Ambipom":{"Normal":4},"Blissey":{"Water":1,"Ice":1},"Mudsdale":{"Ghost":1,"Grass":1},"Toxtricity":{"Normal":5},"Cloyster":{"Electric":2,"Ghost":1},"Hydreigon":{"Steel":2,"Fire":3,"Fairy":2},"Magmortar":{"Water":1,"Grass":1},"Wyrdeer":{"Bug":1},"Decidueye-Hisui":{"Fairy":1,"Fire":1,"Fighting":1,"Electric":1,"Dark":1,"Stellar":1},"Clawitzer":{"Fighting":1,"Dark":1},"Hippowdon":{"Steel":1,"Grass":1},"Bellibolt":{"Electric":2},"Torterra":{"Water":1,"Rock":1,"Grass":1,"Ghost":1,"Electric":1},"Quaquaval":{"Flying":1,"Fire":1,"Steel":1},"Probopass":{"Fighting":2,"Ghost":1},"Houndstone":{"Ghost":2,"Fairy":1},"Klefki":{"Flying":2},"Rhydon":{"Dragon":1,"Grass":1},"Zacian":{"Fire":2,"Psychic":1},"Haxorus":{"Rock":1,"Steel":1,"Poison":1},"Maushold":{"Ghost":1,"Normal":1},"Exeggutor":{"Fairy":1},"Scyther":{"Water":1},"Feraligatr":{"Grass":1},"Giratina":{"Fairy":3,"Electric":1},"Meowscarada":{"Grass":4,"Poison":1,"Normal":1},"Glaceon":{"Dragon":1},"Grafaiai":{"Fighting":1},"Cacturne":{"Electric":1},"Tinkaton":{"Fairy":1,"Dragon":2},"Lurantis":{"Poison":1,"Water":2,"Normal":2,"Electric":1},"Cetitan":{"Water":3,"Electric":1},"Gardevoir":{"Psychic":2},"Arboliva":{"Electric":1},"Golem":{"Normal":1},"Mandibuzz":{"Poison":2,"Fire":1},"Regirock":{"Rock":1,"Grass":1},"Bruxish":{"Water":2,"Fairy":1},"Camerupt":{"Ghost":1,"Grass":1},"Kingdra":{"Water":1,"Steel":1},"Tatsugiri-Droopy":{"Water":1},"Barraskewda":{"Water":1,"Grass":1},"Cobalion":{"Normal":1},"Golurk":{"Fighting":2},"Ariados":{"Bug":1},"Altaria":{"Dragon":1},"Spectrier":{"Dark":1,"Normal":1,"Fairy":1},"Palafin":{"Water":1},"Lilligant":{"Water":1},"Scovillain":{"Fire":2,"Grass":1},"Sandslash-Alola":{"Fire":1,"Dark":1,"Ghost":1},"Leavanny":{"Ghost":1},"Alcremie":{"Steel":1},"Poliwrath":{"Poison":1},"Mimikyu":{"Ghost":1,"Grass":1},"Bisharp":{"Fairy":2,"Flying":1},"Toxicroak":{"Fire":1},"Azelf":{"Fighting":1},"Raichu":{"Electric":1,"Flying":1,"Water":1,"Ghost":1},"Perrserker":{"Ghost":1},"Wigglytuff":{"Stellar":1},"Servine":{"Grass":1},"Zamazenta":{"Water":1},"Ampharos":{"Electric":1},"Illumise":{"Dark":1},"Bombirdier":{"Rock":1},"Bellossom":{"Ghost":1},"Lapras":{"Grass":1,"Fire":1},"Duraludon":{"Stellar":1,"Fairy":1,"Flying":1},"Hawlucha":{"Steel":1},"Clefable":{"Steel":1},"Flareon":{"Normal":1,"Fire":1},"Staraptor":{"Bug":1},"Lycanroc-Dusk":{"Grass":1},"Pawmot":{"Electric":1},"Bastiodon":{"Fairy":1},"Qwilfish-Hisui":{"Water":1},"Houndoom":{"Fire":1},"Tauros-Paldea-Aqua":{"Ice":1},"Mightyena":{"Ghost":1},"Ursaring":{"Normal":1},"Cyclizar":{"Dragon":1,"Ghost":1},"Raikou":{"Fairy":1},"Decidueye":{"Grass":1},"Tatsugiri-Stretchy":{"Steel":1},"Florges-White":{"Steel":1},"Sawsbuck":{"Dark":1},"Alomomola":{"Grass":1},"Squawkabilly-White":{"Normal":1},"Gengar":{"Ghost":1},"Basculegion-F":{"Ice":1},"Pikachu":{"Fairy":1},"Blastoise":{"Grass":2}}