{"Tauros-Paldea-Aqua":{"Steel":4,"Ghost":3,"Water":3,"Stellar":4,"Grass":2,"Ground":1},"Gholdengo":{"Water":54,"Dragon":47,"Steel":149,"Flying":4,"Normal":6,"Fairy":11,"Ghost":1,"Stellar":2},"Indeedee-F":{"Fairy":18,"Grass":8,"Steel":2,"Ghost":1,"Water":1,"Dragon":1},"Farigiraf":{"Fairy":23,"Ghost":1,"Water":3,"Fire":1,"Normal":8,"Grass":4,"Dragon":1},"Kingambit":{"Dragon":6,"Fairy":5,"Dark":31,"Fire":4,"Flying":20,"Water":2,"Ghost":1},"Incineroar":{"Ghost":53,"Water":13,"Dragon":5,"Grass":27,"Flying":2,"Fairy":1,"Fire":1,"Dark":1},"Ursaluna-Bloodmoon":{"Normal":248,"Grass":5,"Ground":4,"Ghost":3,"Poison":1,"Fairy":3},"Jolteon":{"Flying":1,"Water":1,"Ice":1},"Basculegion":{"Water":20,"Grass":6,"Ghost":6,"Normal":1,"Dark":1,"Fairy":4},"Smeargle":{"Ghost":3,"Grass":4},"Sneasler":{"Flying":8,"Rock":1,"Grass":1,"Fighting":1,"Ghost":1},"Typhlosion-Hisui":{"Fire":20,"Grass":2},"Coalossal":{"Fire":3,"Grass":2},"Tyranitar":{"Flying":39,"Grass":17,"Fairy":4,"Psychic":2,"Ghost":3,"Dragon":1,"Poison":2},"Tatsugiri-Stretchy":{"Water":1},"Armarouge":{"Dark":2,"Grass":36,"Psychic":8,"Fighting":1,"Fire":2},"Milotic":{"Dragon":4,"Grass":2,"Fairy":3,"Poison":1},"Amoonguss":{"Fairy":7,"Water":48,"Dark":8,"Dragon":2,"Steel":2,"Ground":1,"Ghost":2},"Corviknight":{"Fighting":1,"Dragon":3,"Water":1,"Ground":1,"Flying":1,"Fire":2},"Palafin-Hero":{"Water":89,"Grass":5,"Fire":1},"Maushold":{"Ghost":10,"Normal":1,"Grass":1},"Salamence":{"Steel":8,"Fairy":1,"Flying":3,"Stellar":1,"Fire":2,"Water":1},"Glimmora":{"Grass":46,"Stellar":1,"Rock":2,"Ground":2},"Stonjourner":{"Fighting":5,"Rock":1,"Ghost":1},"Toxtricity-Low-Key":{"Normal":1,"Dark":1},"Annihilape":{"Fire":81,"Steel":8,"Fairy":3,"Water":8,"Normal":3,"Dragon":3,"Fighting":3,"Ghost":3,"Dark":2,"Grass":7,"Electric":2,"Rock":1,"Poison":1,"Stellar":1},"Kommo-o":{"Fire":11,"Steel":41,"Fairy":1,"Ghost":1,"Normal":2,"Dragon":2},"Baxcalibur":{"Poison":12,"Steel":2,"Water":6,"Fire":1,"Dragon":6,"Ghost":1,"Ground":1,"Fairy":1},"Arcanine-Hisui":{"Normal":10,"Fairy":4,"Water":5,"Psychic":2,"Grass":12,"Ghost":2},"Gyarados":{"Grass":1,"Steel":1,"Dark":1,"Flying":3,"Water":1,"Ground":1},"Archaludon":{"Fairy":42,"Grass":61,"Ghost":4,"Bug":6,"Steel":3,"Stellar":2,"Flying":3,"Electric":2},"Sinistcha-Masterpiece":{"Water":5,"Steel":1,"Normal":1,"Fire":2,"Grass":1},"Porygon2":{"Fairy":11,"Flying":9,"Ghost":7,"Poison":9,"Electric":3,"Water":1,"Ground":1},"Garchomp":{"Steel":11,"Ground":7,"Fire":7,"Fairy":2,"Poison":1},"Sylveon":{"Fire":13,"Ground":5,"Fairy":9,"Water":3,"Normal":1,"Steel":5},"Palafin":{"Water":32,"Grass":2},"Maushold-Four":{"Ghost":14,"Normal":1,"Grass":1},"Dragapult":{"Ghost":16,"Fairy":3,"Dragon":13,"Steel":6,"Fire":3,"Grass":1},"Torkoal":{"Fire":81,"Grass":2,"Ghost":1},"Hydreigon":{"Steel":22,"Fire":11,"Electric":1,"Poison":19,"Dragon":3,"Ghost":2,"Fairy":1,"Grass":1},"Rillaboom":{"Fire":40,"Water":10,"Grass":24,"Normal":1,"Poison":2,"Dark":1,"Ghost":2,"Dragon":1,"Rock":1},"Ursaluna":{"Normal":10,"Ghost":14,"Grass":3,"Fairy":2,"Dragon":5,"Ground":1,"Poison":1},"Gastrodon":{"Flying":1,"Grass":1,"Fire":4,"Steel":1},"Dragonite":{"Normal":29,"Flying":9,"Fire":1},"Altaria":{"Fairy":1},"Dondozo":{"Grass":31,"Dragon":13,"Flying":4,"Fighting":1,"Steel":5,"Electric":1,"Water":1},"Hatterene":{"Steel":4,"Psychic":14,"Stellar":3,"Water":2,"Dark":1},"Overqwil":{"Normal":1,"Poison":1,"Water":2,"Bug":1},"Tatsugiri":{"Steel":4,"Water":1,"Dragon":1,"Ghost":1},"Talonflame":{"Flying":7,"Ghost":9,"Steel":3},"Slaking":{"Ghost":2,"Fighting":1,"Grass":1,"Fairy":1},"Azumarill":{"Water":3,"Grass":3,"Electric":1,"Steel":1},"Sinistcha":{"Fire":4,"Water":8,"Fairy":3,"Dark":2,"Dragon":1,"Poison":1},"Frosmoth":{"Ground":5,"Electric":3,"Water":5},"Comfey":{"Steel":2},"Mamoswine":{"Ground":2,"Ghost":1,"Fire":1,"Grass":1},"Houndoom":{"Grass":1},"Umbreon":{"Steel":2},"Basculegion-F":{"Water":1},"Flygon":{"Steel":1},"Ribombee":{"Ghost":1,"Electric":1},"Porygon-Z":{"Ice":9,"Fighting":1,"Normal":1},"Gardevoir":{"Fire":3,"Water":2,"Psychic":3,"Dark":1},"Primarina":{"Grass":29,"Ghost":3,"Water":6,"Steel":13,"Dragon":4,"Poison":6,"Fairy":2,"Ground":1,"Fire":5},"Goodra-Hisui":{"Water":7,"Fighting":1,"Fairy":1,"Flying":2,"Steel":2},"Rotom-Frost":{"Ice":1},"Hydrapple":{"Water":1,"Steel":1,"Fire":1},"Volcarona":{"Fairy":2,"Dragon":10,"Water":11,"Grass":30,"Poison":1,"Flying":1,"Normal":2,"Dark":1,"Ghost":1,"Steel":1},"Pelipper":{"Steel":4,"Stellar":6,"Flying":5,"Dragon":1,"Ghost":13,"Grass":2,"Dark":1,"Electric":1},"Araquanid":{"Water":7,"Grass":1},"Espeon":{"Normal":1,"Fairy":1,"Psychic":1},"Glaceon":{"Water":14,"Fire":1,"Ground":1},"Dusclops":{"Dark":5},"Garganacl":{"Poison":4,"Ghost":9,"Grass":3,"Water":1},"Rotom-Wash":{"Grass":4,"Electric":1,"Fairy":1,"Fire":2,"Ghost":2},"Ninetales-Alola":{"Ghost":11,"Water":4,"Dragon":1,"Ice":1,"Poison":1,"Fire":2,"Steel":1},"Weezing":{"Poison":1,"Dark":2,"Grass":3,"Ghost":2},"Ceruledge":{"Grass":18,"Fairy":2,"Fire":2},"Serperior":{"Fire":3,"Stellar":3,"Poison":2,"Water":1},"Meowscarada":{"Grass":8,"Stellar":4,"Fire":1,"Ghost":1},"Blaziken":{"Water":4,"Fire":1},"Whimsicott":{"Water":7,"Ghost":2,"Dark":2},"Flareon":{"Normal":2},"Lycanroc":{"Fighting":1,"Rock":1,"Ghost":1},"Excadrill":{"Ground":7,"Fire":1,"Stellar":3,"Grass":2,"Dragon":1},"Samurott-Hisui":{"Steel":1,"Grass":2,"Water":1,"Fire":1},"Bronzong":{"Dark":1,"Steel":1,"Flying":1,"Fighting":1},"Skeledirge":{"Water":4,"Fairy":2,"Ghost":1,"Fire":1,"Grass":3,"Dark":1,"Normal":1},"Mimikyu-Busted":{"Ghost":1},"Floatzel":{"Water":1},"Dachsbun":{"Steel":1,"Grass":1},"Cetitan":{"Ground":3,"Water":6,"Ice":1},"Charizard":{"Ground":1,"Fire":4,"Flying":1},"Houndstone":{"Ghost":3,"Dark":1,"Fighting":1},"Gallade":{"Fighting":2,"Rock":1,"Grass":8,"Fire":3,"Psychic":1,"Stellar":1,"Steel":4},"Gogoat":{"Fire":1},"Pawmot":{"Electric":3},"Conkeldurr":{"Steel":3,"Water":1,"Dragon":1,"Fighting":1,"Fire":1},"Beartic":{"Water":2,"Ground":1},"Kilowattrel":{"Electric":5,"Ghost":2},"Empoleon":{"Grass":2,"Steel":1,"Flying":2,"Fairy":1,"Ice":1},"Tauros-Paldea-Blaze":{"Water":2,"Dragon":1},"Magmar":{"Grass":4,"Water":1},"Froslass":{"Ice":2},"Torterra":{"Grass":2},"Toxtricity":{"Normal":2},"Braviary-Hisui":{"Psychic":10},"Orthworm":{"Fire":2,"Rock":1},"Chandelure":{"Ghost":1,"Grass":3},"Ludicolo":{"Electric":1,"Stellar":3,"Water":1},"Snorlax":{"Ghost":6,"Water":3},"Arcanine":{"Dragon":1,"Grass":1},"Grimmsnarl":{"Ghost":6,"Steel":2},"Tsareena":{"Water":1,"Ice":1,"Flying":1},"Clefable":{"Water":4,"Steel":3},"Slowpoke":{"Poison":1},"Magnezone":{"Water":1,"Electric":1},"Murkrow":{"Ghost":9,"Steel":1,"Flying":1},"Politoed":{"Fire":1,"Steel":1,"Grass":2},"Quaquaval":{"Water":2,"Steel":1},"Chesnaught":{"Fire":7,"Ghost":1,"Poison":3},"Metagross":{"Steel":1,"Normal":1,"Water":2,"Dragon":2},"Gastrodon-East":{"Fire":4},"Tropius":{"Dragon":1},"Gothitelle":{"Water":2,"Fairy":2},"Weavile":{"Ghost":1},"Bruxish":{"Psychic":1},"Kingdra":{"Steel":3,"Water":2,"Poison":1,"Grass":1},"Toxapex":{"Fairy":1,"Dark":1},"Rampardos":{"Rock":1,"Fighting":1},"Poliwrath":{"Grass":2},"Cloyster":{"Ice":1},"Gliscor":{"Water":2,"Ghost":1},"Rotom-Heat":{"Grass":1,"Electric":1,"Fire":1},"Lucario":{"Fire":1,"Normal":1},"Brambleghast":{"Ghost":4},"Staraptor":{"Ghost":1,"Flying":1},"Braviary":{"Steel":1,"Rock":1},"Indeedee":{"Psychic":4,"Fairy":1},"Scizor":{"Water":4,"Steel":1},"Venusaur":{"Poison":1,"Fire":1,"Stellar":1,"Water":1,"Ground":1},"Lilligant-Hisui":{"Ghost":2},"Mienshao":{"Dark":2,"Fighting":1},"Rhyperior":{"Grass":2},"Breloom":{"Ghost":1},"Infernape":{"Fighting":1,"Grass":1},"Cinderace":{"Fire":1},"Raichu":{"Fairy":1},"Yanmega":{"Ground":1,"Ghost":1},"Donphan":{"Ice":1,"Ground":1},"Rabsca":{"Rock":1,"Fairy":1},"Quagsire":{"Grass":1},"Reuniclus":{"Fighting":1,"Psychic":1},"Goodra":{"Steel":1,"Water":1,"Stellar":1},"Lokix":{"Fighting":1},"Gengar":{"Ghost":2,"Grass":1},"Malamar":{"Poison":2},"Alcremie":{"Steel":1},"Kleavor":{"Stellar":1},"Sceptile":{"Fairy":1},"Delphox":{"Grass":2,"Fighting":1},"Typhlosion":{"Fire":1,"Ghost":1},"Muk-Alola":{"Grass":1},"Klefki":{"Fairy":1},"Vaporeon":{"Grass":1},"Cinccino":{"Grass":2},"Zoroark-Hisui":{"Normal":1},"Flamigo":{"Steel":1},"Oricorio-Sensu":{"Fighting":1},"Mimikyu":{"Ghost":1},"Bellibolt":{"Grass":1,"Flying":1,"Electric":1},"Drednaw":{"Grass":4},"Bronzor":{"Steel":1},"Haxorus":{"Fire":1},"Slowking-Galar":{"Ice":1},"Noivern":{"Normal":1},"Mudsdale":{"Fire":1},"Lilligant":{"Ghost":1},"Oranguru":{"Water":1,"Grass":1},"Weezing-Galar":{"Bug":1},"Rhydon":{"Fairy":1},"Abomasnow":{"Ice":1,"Water":1},"Cryogonal":{"Electric":2},"Hawlucha":{"Flying":1},"Blastoise":{"Grass":2,"Ghost":1},"Decidueye-Hisui":{"Fire":1},"Hitmonchan":{"Fighting":1,"Steel":1},"Hariyama":{"Steel":1,"Normal":1},"Basculin-Blue-Striped":{"Water":1},"Illumise":{"Water":1},"Bisharp":{"Ghost":2},"Ditto":{"Normal":1,"Stellar":1},"Magmortar":{"Fire":2},"Medicham":{"Ghost":1,"Rock":1},"Tatsugiri-Droopy":{"Dragon":1},"Vikavolt":{"Electric":1},"Toxicroak":{"Dark":1},"Oricorio-Pom-Pom":{"Water":1},"Salazzle":{"Ghost":1},"Klawf":{"Rock":1},"Inteleon":{"Flying":1},"Barraskewda":{"Water":1},"Heracross":{"Poison":1},"Spiritomb":{"Poison":1},"Alcremie-Lemon-Cream":{"Steel":1},"Golem-Alola":{"Electric":1},"Krookodile":{"Ghost":1},"Vileplume":{"Dark":1},"Toucannon":{"Steel":1},"Bastiodon":{"Grass":1},"Electabuzz":{"Ghost":1},"Arboliva":{"Ghost":1},"Slowbro":{"Grass":1},"Clefairy":{"Grass":1}}